abstract_github/__init__.py
abstract_github/call_manager.py
abstract_github/rate_limiter.py
abstract_github/safe_call_data.py
abstract_github/utils.py
abstract_github-0.0.0.1.dist-info/LICENSE
abstract_github-0.0.0.1.dist-info/METADATA
abstract_github-0.0.0.1.dist-info/WHEEL
abstract_github-0.0.0.1.dist-info/top_level.txt
abstract_github-0.0.0.1.dist-info/RECORD
